Workbook

Sheet Dashboard
A1: Market Portfolio Risk & Decision Dashboard
A2: Conservative vs. Balanced vs. Growth | Quantitative comparison of return, risk and downside exposure | Data window: Jan 2019 - Dec 2025
B4: CONSERVATIVE PORTFOLIO | D4: BALANCED PORTFOLIO | F4: GROWTH PORTFOLIO
B5: =Data!B2 -> 0.105047 | D5: =Data!C2 -> 0.123237 | F5: =Data!D2 -> 0.187285
B6: Annualized Return | D6: Annualized Return | F6: Annualized Return
B7: Sharpe Ratio | C7: =Data!B4 -> 0.971717 | D7: Sharpe Ratio | E7: =Data!C4 -> 0.977689 | F7: Sharpe Ratio | G7: =Data!D4 -> 0.955622
B8: Sortino Ratio | C8: =Data!B12 -> 1.587498 | D8: Sortino Ratio | E8: =Data!C12 -> 1.561576 | F8: Sortino Ratio | G8: =Data!D12 -> 1.522916
B9: Max Drawdown | C9: =Data!B10 -> -0.250688 | D9: Max Drawdown | E9: =Data!C10 -> -0.248956 | F9: Max Drawdown | G9: =Data!D10 -> -0.303071
B10: Beta | C10: =Data!B5 -> 0.369071 | D10: Beta | E10: =Data!C5 -> 0.572608 | F10: Beta | G10: =Data!D5 -> 0.961729
A13: Performance & Risk Comparison
A14: Portfolio | B14: Annualized Return | C14: Annualized Volatility | D14: Sharpe Ratio | E14: Sortino Ratio | F14: Beta | G14: Max Drawdown | H14: Hist. VaR (95%)
A15: Conservative | B15: =Data!B2 -> 0.105047 | C15: =Data!B3 -> 0.108104 | D15: =Data!B4 -> 0.971717 | E15: =Data!B12 -> 1.587498 | F15: =Data!B5 -> 0.369071 | G15: =Data!B10 -> -0.250688 | H15: =Data!B8 -> -0.010521
A16: Balanced | B16: =Data!C2 -> 0.123237 | C16: =Data!C3 -> 0.126049 | D16: =Data!C4 -> 0.977689 | E16: =Data!C12 -> 1.561576 | F16: =Data!C5 -> 0.572608 | G16: =Data!C10 -> -0.248956 | H16: =Data!C8 -> -0.011563
A17: Growth | B17: =Data!D2 -> 0.187285 | C17: =Data!D3 -> 0.195982 | D17: =Data!D4 -> 0.955622 | E17: =Data!D12 -> 1.522916 | F17: =Data!D5 -> 0.961729 | G17: =Data!D10 -> -0.303071 | H17: =Data!D8 -> -0.018348
A54: Tip: Open the "Decision Tool" tab to set your own priorities (return, volatility, downside protection, market sensitivity) and get a weighted, ranked recommendation.

Sheet Decision Tool
A1: Interactive Portfolio Decision Tool
A2: Set your priorities below - the recommendation updates automatically.
A4: Investor Risk Tolerance (label only) | B4: Balanced | D4: (descriptive only - drive the score with the weights below)
A6: Step 1 - Set Your Priority Weights (0-100 each; relative weight, do not need to sum to 100)
B7: Return Priority | C7: Low Volatility | D7: Downside Protection | E7: Low Market Sensitivity
B8: 25 | C8: 25 | D8: 25 | E8: 25
A10: Step 2 - Weighted Score & Ranking (0-1 scale, relative to the 3 portfolios; higher is better)
A11: Portfolio | B11: Return Score | C11: Volatility Score | D11: Downside Score | E11: Market Score | F11: Weighted Total | G11: Rank
A12: Conservative | B12: =AVERAGE((Data!B2-MIN(Data!$B2:$D2))/(MAX(Data!$B2:$D2)-MIN(Data!$B2:$D2)),(Data!B4-MIN(Data!$B4:$D4))/(MAX(Data!$B4:$D4)-MIN(Data!$B4:$D4)),(Data!B12-MIN(Data!$B12:$D12))/(MAX(Data!$B12:$D12)-MIN(Data!$B12:$D12))) -> 0.57645655 | C12: =AVERAGE((MAX(Data!$B3:$D3)-Data!B3)/(MAX(Data!$B3:$D3)-MIN(Data!$B3:$D3)),(MAX(Data!$B11:$D11)-Data!B11)/(MAX(Data!$B11:$D11)-MIN(Data!$B11:$D11))) -> 1 | D12: =AVERAGE((Data!B8-MIN(Data!$B8:$D8))/(MAX(Data!$B8:$D8)-MIN(Data!$B8:$D8)),(Data!B9-MIN(Data!$B9:$D9))/(MAX(Data!$B9:$D9)-MIN(Data!$B9:$D9)),(Data!B10-MIN(Data!$B10:$D10))/(MAX(Data!$B10:$D10)-MIN(Data!$B10:$D10))) -> 0.98933136 | E12: =(MAX(Data!$B5:$D5)-Data!B5)/(MAX(Data!$B5:$D5)-MIN(Data!$B5:$D5)) -> 1 | F12: =(B12*$B$8+C12*$C$8+D12*$D$8+E12*$E$8)/SUM($B$8:$E$8) -> 0.89144698 | G12: =RANK(F12,$F$12:$F$14,0) -> 1
A13: Balanced | B13: =AVERAGE((Data!C2-MIN(Data!$B2:$D2))/(MAX(Data!$B2:$D2)-MIN(Data!$B2:$D2)),(Data!C4-MIN(Data!$B4:$D4))/(MAX(Data!$B4:$D4)-MIN(Data!$B4:$D4)),(Data!C12-MIN(Data!$B12:$D12))/(MAX(Data!$B12:$D12)-MIN(Data!$B12:$D12))) -> 0.60660203 | C13: =AVERAGE((MAX(Data!$B3:$D3)-Data!C3)/(MAX(Data!$B3:$D3)-MIN(Data!$B3:$D3)),(MAX(Data!$B11:$D11)-Data!C11)/(MAX(Data!$B11:$D11)-MIN(Data!$B11:$D11))) -> 0.73288447 | D13: =AVERAGE((Data!C8-MIN(Data!$B8:$D8))/(MAX(Data!$B8:$D8)-MIN(Data!$B8:$D8)),(Data!C9-MIN(Data!$B9:$D9))/(MAX(Data!$B9:$D9)-MIN(Data!$B9:$D9)),(Data!C10-MIN(Data!$B10:$D10))/(MAX(Data!$B10:$D10)-MIN(Data!$B10:$D10))) -> 0.88015923 | E13: =(MAX(Data!$B5:$D5)-Data!C5)/(MAX(Data!$B5:$D5)-MIN(Data!$B5:$D5)) -> 0.65656922 | F13: =(B13*$B$8+C13*$C$8+D13*$D$8+E13*$E$8)/SUM($B$8:$E$8) -> 0.71905374 | G13: =RANK(F13,$F$12:$F$14,0) -> 2
A14: Growth | B14: =AVERAGE((Data!D2-MIN(Data!$B2:$D2))/(MAX(Data!$B2:$D2)-MIN(Data!$B2:$D2)),(Data!D4-MIN(Data!$B4:$D4))/(MAX(Data!$B4:$D4)-MIN(Data!$B4:$D4)),(Data!D12-MIN(Data!$B12:$D12))/(MAX(Data!$B12:$D12)-MIN(Data!$B12:$D12))) -> 0.33333333 | C14: =AVERAGE((MAX(Data!$B3:$D3)-Data!D3)/(MAX(Data!$B3:$D3)-MIN(Data!$B3:$D3)),(MAX(Data!$B11:$D11)-Data!D11)/(MAX(Data!$B11:$D11)-MIN(Data!$B11:$D11))) -> 0 | D14: =AVERAGE((Data!D8-MIN(Data!$B8:$D8))/(MAX(Data!$B8:$D8)-MIN(Data!$B8:$D8)),(Data!D9-MIN(Data!$B9:$D9))/(MAX(Data!$B9:$D9)-MIN(Data!$B9:$D9)),(Data!D10-MIN(Data!$B10:$D10))/(MAX(Data!$B10:$D10)-MIN(Data!$B10:$D10))) -> 0 | E14: =(MAX(Data!$B5:$D5)-Data!D5)/(MAX(Data!$B5:$D5)-MIN(Data!$B5:$D5)) -> 0 | F14: =(B14*$B$8+C14*$C$8+D14*$D$8+E14*$E$8)/SUM($B$8:$E$8) -> 0.083333333 | G14: =RANK(F14,$F$12:$F$14,0) -> 3
A16: ="Recommended Portfolio: " & INDEX($A$12:$A$14,MATCH(1,$G$12:$G$14,0)) & " (Weighted Score: " & TEXT(INDEX($F$12:$F$14,MATCH(1,$G$12:$G$14,0)),"0.000") & ")" -> Recommended Portfolio: Conservative (Weighted Score: 0.891)
A18: How this works: - Each metric is min-max normalized across the 3 portfolios (0 = worst, 1 = best), so scores are relative, not absolute. - Return Score blends Annualized Return, Sharpe Ratio and Sortino Ratio. - Volatility Score rewards lower Annualized Volatility and lower Maximum Rolling Volatility. - Downside Score rewards a less-negative Historical VaR (95%), Expected Shortfall (95%) and Maximum Drawdown. - Market Score rewards a lower Beta (less sensitivity to the S&P 500). - Weighted Total = weighted average of the four sub-scores, using the weights you set in Step 1. Rank 1 = best fit for your stated priorities. This is a quantitative fit-to-preferences tool based on historical data (Jan 2019 - Dec 2025) — not investment advice or a forecast.

Sheet Performance
A1: Performance Summary
A2: Return and risk-adjusted return measures, Jan 2019 - Dec 2025
A4: Portfolio | B4: Annualized Return | C4: Annualized Volatility | D4: Sharpe Ratio | E4: Sortino Ratio | F4: Treynor Ratio | G4: Jensen's Alpha
A5: Conservative | B5: =Data!B2 -> 0.105047 | C5: =Data!B3 -> 0.108104 | D5: =Data!B4 -> 0.971717 | E5: =Data!B12 -> 1.587498 | F5: =Data!B6 -> 0.284624 | G5: =Data!B7 -> 0.039161
A6: Balanced | B6: =Data!C2 -> 0.123237 | C6: =Data!C3 -> 0.126049 | D6: =Data!C4 -> 0.977689 | E6: =Data!C12 -> 1.561576 | F6: =Data!C6 -> 0.215221 | G6: =Data!C7 -> 0.021016
A7: Growth | B7: =Data!D2 -> 0.187285 | C7: =Data!D3 -> 0.195982 | D7: =Data!D4 -> 0.955622 | E7: =Data!D12 -> 1.522916 | F7: =Data!D6 -> 0.194737 | G7: =Data!D7 -> 0.015599
A27: Beta is on the Risk Analytics tab alongside market-sensitivity measures.

Sheet Risk Analytics
A1: Risk Analytics
A2: Volatility, tail risk and drawdown measures, Jan 2019 - Dec 2025
A4: Portfolio | B4: Beta | C4: Historical VaR (95%) | D4: Expected Shortfall (95%) | E4: Maximum Drawdown | F4: Maximum Rolling Volatility
A5: Conservative | B5: =Data!B5 -> 0.369071 | C5: =Data!B8 -> -0.010521 | D5: =Data!B9 -> -0.015438 | E5: =Data!B10 -> -0.250688 | F5: =Data!B11 -> 0.32307
A6: Balanced | B6: =Data!C5 -> 0.572608 | C6: =Data!C8 -> -0.011563 | D6: =Data!C9 -> -0.018586 | E6: =Data!C10 -> -0.248956 | F6: =Data!C11 -> 0.44979
A7: Growth | B7: =Data!D5 -> 0.961729 | C7: =Data!D8 -> -0.018348 | D7: =Data!D9 -> -0.029343 | E7: =Data!D10 -> -0.303071 | F7: =Data!D11 -> 0.707038

Sheet Stress Testing
A1: Stress-Period Testing
A2: Portfolio behaviour in two historical stress windows
A4: Portfolio | B4: 2020 Stress Period Return (Feb-Jun) | C4: 2022 Annual Return
A5: Conservative | B5: =Data!B13 -> 0.084777 | C5: =Data!B14 -> -0.197331
A6: Balanced | B6: =Data!C13 -> 0.052294 | C6: =Data!C14 -> -0.199534
A7: Growth | B7: =Data!D13 -> 0.075082 | C7: =Data!D14 -> -0.265425
F10: Feb-Jun 2020: COVID-19 drawdown and recovery. 2022: broad rate-driven equity and bond sell-off.

Sheet Asset Allocation
A1: Asset Allocation
A2: Strategic weights underlying each portfolio
A4: Asset | B4: Conservative | C4: Balanced | D4: Growth
A5: SPY - US Large-Cap Equity | B5: =Data!B19 -> 0.4 | C5: =Data!C19 -> 0.6 | D5: =Data!D19 -> 0.4
A6: QQQ - Nasdaq-100 Growth Equity | B6: =Data!B20 -> 0 | C6: =Data!C20 -> 0 | D6: =Data!D20 -> 0.5
A7: TLT - 20+ Yr US Treasuries | B7: =Data!B21 -> 0.4 | C7: =Data!C21 -> 0.3 | D7: =Data!D21 -> 0.1
A8: GLD - Gold | B8: =Data!B22 -> 0.2 | C8: =Data!C22 -> 0.1 | D8: =Data!D22 -> 0
A9: Total | B9: =SUM(B5:B8) -> 1 | C9: =SUM(C5:C8) -> 1 | D9: =SUM(D5:D8) -> 1

Sheet Methodology
A1: Methodology & Assumptions
A2: How every metric on this workbook is calculated
A4: Metric | B4: Methodology
A5: Annualized Return | B5: Mean daily return x 252
A6: Annualized Volatility | B6: Daily standard deviation x sqrt(252)
A7: Sharpe Ratio | B7: Annualized Return / Annualized Volatility; assumes 0% risk-free rate
A8: Sortino Ratio | B8: Annualized Return / Annualized Downside Deviation; simplified downside calculation
A9: Beta | B9: Covariance of portfolio returns with SPY / Variance of SPY
A10: Treynor Ratio | B10: Annualized Return / Beta; assumes 0% risk-free rate
A11: Jensen's Alpha | B11: Portfolio Return - (Beta x SPY Return); assumes 0% risk-free rate
A12: Historical VaR (95%) | B12: 5th percentile of daily portfolio returns
A13: Expected Shortfall (95%) | B13: Average return of observations at or below the 95% VaR threshold
A14: Maximum Drawdown | B14: Largest decline from a previous cumulative-return peak
A15: Maximum Rolling Volatility | B15: 30-trading-day rolling standard deviation x sqrt(252)
... A18: Decision Tool scores | B18: Each metric min-max normalized across the 3 portfolios (0=worst, 1=best), then averaged into 4 sub-scores and combined using user-set weights
A21: Data source & scope
A22: Universe | B22: SPY (US equity), QQQ (Nasdaq-100), TLT (20+yr Treasuries), GLD (gold)
A23: Data window | B23: Jan 2019 - Dec 2025, daily adjusted close, dividends reinvested
A24: Source | B24: Yahoo Finance (yfinance)
A25: Portfolio weights | B25: Conservative: 40% SPY / 40% TLT / 20% GLD. Balanced: 60% SPY / 30% TLT / 10% GLD. Growth: 40% SPY / 50% QQQ / 10% TLT.
A26: Scope | B26: Historical analysis only - not a forecast, recommendation, or investment advice.

Sheet Data
A1: Metric | B1: Conservative | C1: Balanced | D1: Growth | F1: Source data - every figure on the other tabs links back to this sheet.
A2: Annualized Return | B2: 0.105047 | C2: 0.123237 | D2: 0.187285
A3: Annualized Volatility | B3: 0.108104 | C3: 0.126049 | D3: 0.195982
A4: Sharpe Ratio | B4: 0.971717 | C4: 0.977689 | D4: 0.955622
A5: Beta | B5: 0.369071 | C5: 0.572608 | D5: 0.961729
A6: Treynor Ratio | B6: 0.284624 | C6: 0.215221 | D6: 0.194737
A7: Jensen's Alpha | B7: 0.039161 | C7: 0.021016 | D7: 0.015599
A8: Historical VaR (95%) | B8: -0.010521 | C8: -0.011563 | D8: -0.018348
A9: Expected Shortfall (95%) | B9: -0.015438 | C9: -0.018586 | D9: -0.029343
A10: Maximum Drawdown | B10: -0.250688 | C10: -0.248956 | D10: -0.303071
A11: Maximum Rolling Volatility | B11: 0.32307 | C11: 0.44979 | D11: 0.707038
A12: Sortino Ratio | B12: 1.587498 | C12: 1.561576 | D12: 1.522916
A13: 2020 Stress Period Return | B13: 0.084777 | C13: 0.052294 | D13: 0.075082
A14: 2022 Annual Return | B14: -0.197331 | C14: -0.199534 | D14: -0.265425
A17: Asset Allocation Weights
A18: Asset | B18: Conservative | C18: Balanced | D18: Growth
A19: SPY | B19: 0.4 | C19: 0.6 | D19: 0.4
A20: QQQ | B20: 0 | C20: 0 | D20: 0.5
A21: TLT | B21: 0.4 | C21: 0.3 | D21: 0.1
A22: GLD | B22: 0.2 | C22: 0.1 | D22: 0
A24: Data window | B24: Jan 2019 - Dec 2025 (daily total-return series, dividends reinvested)
A25: Universe | B25: SPY (US equity), QQQ (Nasdaq-100), TLT (20+yr Treasuries), GLD (gold)
A26: Source | B26: Yahoo Finance (yfinance) daily adjusted close; project-supplied, not re-verified here
